{
  "asOf": "2026-06-30 20:06 UTC 기준 · 카테고리당 top 5건",
  "items": [
    {
      "category": "fsd",
      "categoryLabel": "FSD · 자율·로보택시",
      "time": "4m ago",
      "pubDate": "2026-06-30T20:01:54.000Z",
      "title": "Lars is saying Tesla is preparing for massive scale in real-world AI products: Cybercab, Robotaxi, Optimus, factory a…",
      "body": "Lars is saying Tesla is preparing for massive scale in real-world AI products: Cybercab, Robotaxi, Optimus, factory automation, service automation, and future products he would not name. His core message is that people a…",
      "sourceName": "Whole Mars (X)",
      "sourceLabel": "press",
      "slug": "",
      "summary": "",
      "href": "https://x.com/wholemars/status/2072048001435181294"
    },
    {
      "category": "musk",
      "categoryLabel": "ELON · 일론 소식",
      "time": "56m ago",
      "pubDate": "2026-06-30T19:09:52.000Z",
      "title": "Neuralink has solved through-dura electrode implantation! This is a very big deal, as it greatly improves the safety …",
      "body": "Neuralink has solved through-dura electrode implantation! This is a very big deal, as it greatly improves the safety and ease of interfacing with the brain. https://t.co/NV59xKAE22",
      "sourceName": "Elon Musk (X)",
      "sourceLabel": "official",
      "slug": "",
      "summary": "",
      "href": "https://x.com/elonmusk/status/2072034905299563005"
    },
    {
      "category": "fsd",
      "categoryLabel": "FSD · 자율·로보택시",
      "time": "1h ago",
      "pubDate": "2026-06-30T18:55:24.000Z",
      "title": "X creators are required to deposit their X payouts in X money. if and when Tesla and SpaceX merge, Robotaxi and Optim…",
      "body": "X creators are required to deposit their X payouts in X money. if and when Tesla and SpaceX merge, Robotaxi and Optimus revenue on the Tesla Network will likely be deposited in X Money as well. this will allow TeslaSpace…",
      "sourceName": "Whole Mars (X)",
      "sourceLabel": "press",
      "slug": "",
      "summary": "",
      "href": "https://x.com/wholemars/status/2072031264601682213"
    },
    {
      "category": "fsd",
      "categoryLabel": "FSD · 자율·로보택시",
      "time": "1h ago",
      "pubDate": "2026-06-30T18:51:28.000Z",
      "title": "there’s nothing going on 😂 i’m just way overdue on trying the driverless robotaxis",
      "body": "there’s nothing going on 😂 i’m just way overdue on trying the driverless robotaxis https://t.co/ZVuXFixleX",
      "sourceName": "Whole Mars (X)",
      "sourceLabel": "press",
      "slug": "",
      "summary": "",
      "href": "https://x.com/wholemars/status/2072030273127035022"
    },
    {
      "category": "musk",
      "categoryLabel": "ELON · 일론 소식",
      "time": "2h ago",
      "pubDate": "2026-06-30T18:32:00.000Z",
      "title": "SpaceX and Tesla Shares Are Trading Like Twins. What It Means for the Stocks.",
      "body": "SpaceX and Tesla Shares Are Trading Like Twins. What It Means for the Stocks. Barron's",
      "sourceName": "Barron's",
      "sourceLabel": "press",
      "slug": "",
      "summary": "",
      "href": "https://www.barrons.com/articles/tesla-stock-price-spacex-merger-c29d6bb4"
    },
    {
      "category": "musk",
      "categoryLabel": "ELON · 일론 소식",
      "time": "2h ago",
      "pubDate": "2026-06-30T18:14:39.000Z",
      "title": "Space entrepreneurs borrow some surprisingly terrestrial tactics",
      "body": "Space entrepreneurs borrow some surprisingly terrestrial tactics Financial Times",
      "sourceName": "Financial Times",
      "sourceLabel": "press",
      "slug": "",
      "summary": "",
      "href": "https://www.ft.com/content/79da150f-5a84-44bb-8e97-b46b958c9699"
    },
    {
      "category": "stock",
      "categoryLabel": "STOCK · 주가·실적",
      "time": "2h ago",
      "pubDate": "2026-06-30T18:13:36.000Z",
      "title": "$TSLA In Asia, the third quarter has begun.",
      "body": "$TSLA In Asia, the third quarter has begun.",
      "sourceName": "Tesla Chan (X)",
      "sourceLabel": "press",
      "slug": "",
      "summary": "",
      "href": "https://x.com/Tslachan/status/2072020744230568077"
    },
    {
      "category": "product",
      "categoryLabel": "PRODUCT · 차량·에너지·옵티머스",
      "time": "2h ago",
      "pubDate": "2026-06-30T18:04:54.000Z",
      "title": "Tesla expands massive safety feature worldwide in latest update",
      "body": "Tesla has expanded the footprint of a massive safety feature worldwide with a recent Software Update labeled as 2026.20.6. The expansion of the “Blind Spot Warning While Parked” feature represents the more widespread ava…",
      "sourceName": "www.teslarati.com",
      "sourceLabel": "press",
      "slug": "",
      "summary": "",
      "href": "https://www.teslarati.com/tesla-expands-massive-safety-feature-worldwide-latest-update/"
    },
    {
      "category": "musk",
      "categoryLabel": "ELON · 일론 소식",
      "time": "2h ago",
      "pubDate": "2026-06-30T17:53:36.000Z",
      "title": "Half price Starlink for people in the Memphis region",
      "body": "Half price Starlink for people in the Memphis region https://t.co/9yIQwIMHPR",
      "sourceName": "Elon Musk (X)",
      "sourceLabel": "official",
      "slug": "",
      "summary": "",
      "href": "https://x.com/elonmusk/status/2072015711635914948"
    },
    {
      "category": "product",
      "categoryLabel": "PRODUCT · 차량·에너지·옵티머스",
      "time": "3h ago",
      "pubDate": "2026-06-30T16:58:45.000Z",
      "title": "Joby, Toyota announce joint venture for air taxi production",
      "body": "Joby, Toyota announce joint venture for air taxi production Reuters",
      "sourceName": "Reuters",
      "sourceLabel": "press",
      "slug": "",
      "summary": "",
      "href": "https://www.reuters.com/business/autos-transportation/joby-toyota-announce-joint-venture-air-taxi-production-2026-06-30/"
    },
    {
      "category": "musk",
      "categoryLabel": "ELON · 일론 소식",
      "time": "3h ago",
      "pubDate": "2026-06-30T16:51:54.000Z",
      "title": "And that’s just the tip of the iceberg",
      "body": "And that’s just the tip of the iceberg https://t.co/Xn5BFWW6Uk",
      "sourceName": "Elon Musk (X)",
      "sourceLabel": "official",
      "slug": "",
      "summary": "",
      "href": "https://x.com/elonmusk/status/2072000185769586922"
    },
    {
      "category": "product",
      "categoryLabel": "PRODUCT · 차량·에너지·옵티머스",
      "time": "3h ago",
      "pubDate": "2026-06-30T16:43:30.000Z",
      "title": "New Tesla Supercharger: Biddeford, ME (8 stalls)",
      "body": "New Tesla Supercharger: Biddeford, ME (8 stalls) https://t.co/jkTAAYRlVx https://t.co/iazeGMVcw8",
      "sourceName": "Tesla Charging (X)",
      "sourceLabel": "official",
      "slug": "",
      "summary": "",
      "href": "https://x.com/TeslaCharging/status/2071998070859129124"
    },
    {
      "category": "fsd",
      "categoryLabel": "FSD · 자율·로보택시",
      "time": "5h ago",
      "pubDate": "2026-06-30T15:17:04.000Z",
      "title": "Tech Weekly: Tesla's FSD tech up for debate, Shell unveils concept car",
      "body": "Tech Weekly: Tesla's FSD tech up for debate, Shell unveils concept car Reuters",
      "sourceName": "Reuters",
      "sourceLabel": "press",
      "slug": "",
      "summary": "",
      "href": "https://mobile.reuters.com/video/watch/idRW375230062026RP1/?chan"
    },
    {
      "category": "fsd",
      "categoryLabel": "FSD · 자율·로보택시",
      "time": "5h ago",
      "pubDate": "2026-06-30T15:17:04.000Z",
      "title": "Tech Weekly: Tesla's FSD tech up for debate, Shell unveils concept car",
      "body": "Tech Weekly: Tesla's FSD tech up for debate, Shell unveils concept car Reuters",
      "sourceName": "Reuters",
      "sourceLabel": "press",
      "slug": "",
      "summary": "",
      "href": "https://www.reuters.com/video/watch/idRW375230062026RP1/"
    },
    {
      "category": "stock",
      "categoryLabel": "STOCK · 주가·실적",
      "time": "6h ago",
      "pubDate": "2026-06-30T14:02:00.000Z",
      "title": "Tesla Stock Falls After Big Gains as Auto Industry Wrestles With Copper Prices",
      "body": "Tesla Stock Falls After Big Gains as Auto Industry Wrestles With Copper Prices Barron's",
      "sourceName": "Barron's",
      "sourceLabel": "press",
      "slug": "",
      "summary": "",
      "href": "https://www.barrons.com/articles/tesla-stock-price-today-copper-a0b9b8b3"
    },
    {
      "category": "product",
      "categoryLabel": "PRODUCT · 차량·에너지·옵티머스",
      "time": "7h ago",
      "pubDate": "2026-06-30T13:27:02.000Z",
      "title": "Volkswagen's crisis in five charts",
      "body": "Volkswagen's crisis in five charts Reuters",
      "sourceName": "Reuters",
      "sourceLabel": "press",
      "slug": "",
      "summary": "",
      "href": "https://www.reuters.com/business/autos-transportation/volkswagens-crisis-five-charts-2026-06-30/"
    },
    {
      "category": "stock",
      "categoryLabel": "STOCK · 주가·실적",
      "time": "8h ago",
      "pubDate": "2026-06-30T12:34:28.000Z",
      "title": "This payments stock could jump as its profit push begins to pay off, Piper Sandler says",
      "body": "This payments stock could jump as its profit push begins to pay off, Piper Sandler says CNBC",
      "sourceName": "CNBC",
      "sourceLabel": "press",
      "slug": "",
      "summary": "",
      "href": "https://www.cnbc.com/2026/06/30/block-could-jump-as-profit-push-begins-to-pay-off-piper-sandler-says.html"
    },
    {
      "category": "stock",
      "categoryLabel": "STOCK · 주가·실적",
      "time": "8h ago",
      "pubDate": "2026-06-30T12:28:34.000Z",
      "title": "Here are Tuesday's biggest analyst calls: Nvidia, Netflix, Tesla, Alphabet, AMD, Sandisk, Block, Broadcom & more",
      "body": "Here are Tuesday's biggest analyst calls: Nvidia, Netflix, Tesla, Alphabet, AMD, Sandisk, Block, Broadcom & more CNBC",
      "sourceName": "CNBC",
      "sourceLabel": "press",
      "slug": "",
      "summary": "",
      "href": "https://www.cnbc.com/2026/06/30/tuesday-biggest-analyst-call-on-wall-street-include-nvidia.html"
    },
    {
      "category": "product",
      "categoryLabel": "PRODUCT · 차량·에너지·옵티머스",
      "time": "8h ago",
      "pubDate": "2026-06-30T12:00:01.000Z",
      "title": "Trump administration's AI crackdown opens door for China to close gap",
      "body": "Trump administration's AI crackdown opens door for China to close gap CNBC",
      "sourceName": "CNBC",
      "sourceLabel": "press",
      "slug": "",
      "summary": "",
      "href": "https://www.cnbc.com/2026/06/30/white-house-ai-china-crackdown.html"
    },
    {
      "category": "stock",
      "categoryLabel": "STOCK · 주가·실적",
      "time": "10h ago",
      "pubDate": "2026-06-30T10:11:05.000Z",
      "title": "Check out Oklo's stock price (OKLO) in real time",
      "body": "Check out Oklo's stock price (OKLO) in real time CNBC",
      "sourceName": "CNBC",
      "sourceLabel": "press",
      "slug": "",
      "summary": "",
      "href": "https://www.cnbc.com/quotes/OKLO"
    }
  ]
}
