{
  "asOf": "2026-06-14 01:40 UTC 기준 · 카테고리당 top 5건",
  "items": [
    {
      "category": "musk",
      "categoryLabel": "ELON · 일론 소식",
      "time": "13m ago",
      "pubDate": "2026-06-14T01:28:04.000Z",
      "title": "FRANZ JOINS Tesla TAKEOVER EUROPE: Nothing hits different than seeing the man who designed every Tesla you’ve ever lo…",
      "body": "FRANZ JOINS Tesla TAKEOVER EUROPE: Nothing hits different than seeing the man who designed every Tesla you’ve ever loved actually show up for the community. In this video, Franz von Holzhausen (@woodhaus2) joins live fro…",
      "sourceName": "Tesla Owners SV (X)",
      "sourceLabel": "press",
      "slug": "",
      "summary": "",
      "href": "https://x.com/teslaownersSV/status/2065969488944914834"
    },
    {
      "category": "product",
      "categoryLabel": "PRODUCT · 차량·에너지·옵티머스",
      "time": "29m ago",
      "pubDate": "2026-06-14T01:12:02.000Z",
      "title": "New Tesla Supercharger: Albuquerque, NM - 12th Street Northwest (24 stalls)",
      "body": "New Tesla Supercharger: Albuquerque, NM - 12th Street Northwest (24 stalls) https://t.co/yx0k2aBUDW https://t.co/xYXKKtxIVN",
      "sourceName": "Tesla Charging (X)",
      "sourceLabel": "official",
      "slug": "",
      "summary": "",
      "href": "https://x.com/TeslaCharging/status/2065965453361700906"
    },
    {
      "category": "fsd",
      "categoryLabel": "FSD · 자율·로보택시",
      "time": "1h ago",
      "pubDate": "2026-06-14T00:21:03.000Z",
      "title": "Tesla stock: FSD approved in Denmark; Elon Musk says this about AI chips",
      "body": "Tesla stock: FSD approved in Denmark; Elon Musk says this about AI chips MSN",
      "sourceName": "MSN",
      "sourceLabel": "press",
      "slug": "",
      "summary": "",
      "href": "https://www.msn.com/en-us/news/technology/tesla-stock-fsd-approved-in-denmark-elon-musk-says-this-about-ai-chips/ar-AA25iq9s"
    },
    {
      "category": "musk",
      "categoryLabel": "ELON · 일론 소식",
      "time": "2h ago",
      "pubDate": "2026-06-13T23:53:34.000Z",
      "title": "Human scale vs Starship",
      "body": "Human scale vs Starship https://t.co/03ZQHluBdR",
      "sourceName": "Tesla Owners SV (X)",
      "sourceLabel": "press",
      "slug": "",
      "summary": "",
      "href": "https://x.com/teslaownersSV/status/2065945705613766668"
    },
    {
      "category": "musk",
      "categoryLabel": "ELON · 일론 소식",
      "time": "2h ago",
      "pubDate": "2026-06-13T23:43:35.000Z",
      "title": "I had a great time at @Tesla Giga Berlin a few days ago, getting to tour the factory, meet with several employees and…",
      "body": "I had a great time at @Tesla Giga Berlin a few days ago, getting to tour the factory, meet with several employees and perhaps most importantly, I got to meet &amp; interview the primary drone operators covering the const…",
      "sourceName": "Joe Tegtmeyer (X)",
      "sourceLabel": "press",
      "slug": "",
      "summary": "",
      "href": "https://x.com/JoeTegtmeyer/status/2065943195930996787"
    },
    {
      "category": "musk",
      "categoryLabel": "ELON · 일론 소식",
      "time": "2h ago",
      "pubDate": "2026-06-13T23:36:05.000Z",
      "title": "When shopping for books for my kid, too many convince young girls to feel bitter, but too few inspire them that they …",
      "body": "When shopping for books for my kid, too many convince young girls to feel bitter, but too few inspire them that they too could become robotic or rocket engineers at Tesla or SpaceX.",
      "sourceName": "Yun-Ta Tsai (X)",
      "sourceLabel": "official",
      "slug": "",
      "summary": "",
      "href": "https://x.com/yunta_tsai/status/2065941307458285774"
    },
    {
      "category": "musk",
      "categoryLabel": "ELON · 일론 소식",
      "time": "2h ago",
      "pubDate": "2026-06-13T23:28:13.000Z",
      "title": "My last day in Bern, Switzerland and who did I run into … none other than Albert Einstein … well, at least a bronze s…",
      "body": "My last day in Bern, Switzerland and who did I run into … none other than Albert Einstein … well, at least a bronze statue of him. If you did not know, he lived and developed his theory of Special Relativity in Bern and …",
      "sourceName": "Joe Tegtmeyer (X)",
      "sourceLabel": "press",
      "slug": "",
      "summary": "",
      "href": "https://x.com/JoeTegtmeyer/status/2065939325968122270"
    },
    {
      "category": "fsd",
      "categoryLabel": "FSD · 자율·로보택시",
      "time": "4h ago",
      "pubDate": "2026-06-13T21:55:19.000Z",
      "title": "From photon to tire friction, every microsecond is accounted for.",
      "body": "From photon to tire friction, every microsecond is accounted for. https://t.co/jHhrnBuPpQ",
      "sourceName": "Yun-Ta Tsai (X)",
      "sourceLabel": "official",
      "slug": "",
      "summary": "",
      "href": "https://x.com/yunta_tsai/status/2065915949220573529"
    },
    {
      "category": "product",
      "categoryLabel": "PRODUCT · 차량·에너지·옵티머스",
      "time": "4h ago",
      "pubDate": "2026-06-13T21:29:36.000Z",
      "title": "New Francis Energy Supercharger: Owasso, OK (4 stalls)  Learn more about Supercharger for Business:",
      "body": "New Francis Energy Supercharger: Owasso, OK (4 stalls) https://t.co/i4luU7sBgu Learn more about Supercharger for Business: https://t.co/sWpIJRrJTy https://t.co/uMEjF4LifR",
      "sourceName": "Tesla Charging (X)",
      "sourceLabel": "official",
      "slug": "",
      "summary": "",
      "href": "https://x.com/TeslaCharging/status/2065909476910379027"
    },
    {
      "category": "fsd",
      "categoryLabel": "FSD · 자율·로보택시",
      "time": "5h ago",
      "pubDate": "2026-06-13T21:10:26.000Z",
      "title": "Tesla Cybercab doors opening and charging",
      "body": "Tesla Cybercab doors opening and charging https://t.co/8SbC4UqRmS",
      "sourceName": "Tesla Owners SV (X)",
      "sourceLabel": "press",
      "slug": "",
      "summary": "",
      "href": "https://x.com/teslaownersSV/status/2065904652986798133"
    },
    {
      "category": "stock",
      "categoryLabel": "STOCK · 주가·실적",
      "time": "6h ago",
      "pubDate": "2026-06-13T19:50:07.000Z",
      "title": "JPMorgan upgrades Tesla with a major price target hike",
      "body": "JPMorgan upgrades Tesla with a major price target hike MSN",
      "sourceName": "MSN",
      "sourceLabel": "press",
      "slug": "",
      "summary": "",
      "href": "https://www.msn.com/en-us/autos/news/jpmorgan-upgrades-tesla-with-a-major-price-target-hike/ar-AA24V56R"
    },
    {
      "category": "stock",
      "categoryLabel": "STOCK · 주가·실적",
      "time": "6h ago",
      "pubDate": "2026-06-13T19:49:13.000Z",
      "title": "Huge News for GM Stock, Tesla Stock, and Ford Stock Investors",
      "body": "Huge News for GM Stock, Tesla Stock, and Ford Stock Investors The Globe and Mail",
      "sourceName": "The Globe and Mail",
      "sourceLabel": "press",
      "slug": "",
      "summary": "",
      "href": "https://www.theglobeandmail.com/investing/markets/stocks/TSLA-Q/pressreleases/2457819/huge-news-for-gm-stock-tesla-stock-and-ford-stock-investors/"
    },
    {
      "category": "stock",
      "categoryLabel": "STOCK · 주가·실적",
      "time": "6h ago",
      "pubDate": "2026-06-13T19:46:14.000Z",
      "title": "Cathie Wood sells $16.2 million of tumbling megacap stock",
      "body": "Cathie Wood sells $16.2 million of tumbling megacap stock thestreet.com",
      "sourceName": "thestreet.com",
      "sourceLabel": "press",
      "slug": "",
      "summary": "",
      "href": "https://www.thestreet.com/investing/stocks/cathie-wood-sells-16-2-million-of-tumbling-megacap-stock"
    },
    {
      "category": "fsd",
      "categoryLabel": "FSD · 자율·로보택시",
      "time": "6h ago",
      "pubDate": "2026-06-13T19:25:24.000Z",
      "title": "It's interesting that software engineers trust their coding agents more than I could trust the parts stamped out from…",
      "body": "It's interesting that software engineers trust their coding agents more than I could trust the parts stamped out from the laser-welded injection molding.",
      "sourceName": "Yun-Ta Tsai (X)",
      "sourceLabel": "official",
      "slug": "",
      "summary": "",
      "href": "https://x.com/yunta_tsai/status/2065878218218078593"
    },
    {
      "category": "product",
      "categoryLabel": "PRODUCT · 차량·에너지·옵티머스",
      "time": "7h ago",
      "pubDate": "2026-06-13T18:37:47.000Z",
      "title": "Tesla delivers first Semi electric truck to Pepsi",
      "body": "Tesla delivers first Semi electric truck to Pepsi Mashable",
      "sourceName": "Mashable",
      "sourceLabel": "press",
      "slug": "",
      "summary": "",
      "href": "https://mashable.com/article/tesla-deliver-semi-elon-musk"
    },
    {
      "category": "stock",
      "categoryLabel": "STOCK · 주가·실적",
      "time": "9h ago",
      "pubDate": "2026-06-13T16:29:42.000Z",
      "title": "$Tesla (TSLA.US)$ Is this all about what people chose to believe?",
      "body": "$Tesla (TSLA.US)$ Is this all about what people chose to believe? Moomoo",
      "sourceName": "Moomoo",
      "sourceLabel": "press",
      "slug": "",
      "summary": "",
      "href": "https://www.moomoo.com/community/feed/tesla-tsla-us-is-this-all-about-what-people-chose-116743745175557"
    },
    {
      "category": "stock",
      "categoryLabel": "STOCK · 주가·실적",
      "time": "11h ago",
      "pubDate": "2026-06-13T15:03:25.000Z",
      "title": "Insider trades: Microsoft, Tesla, Pfizer among notable names",
      "body": "Insider trades: Microsoft, Tesla, Pfizer among notable names Seeking Alpha",
      "sourceName": "Seeking Alpha",
      "sourceLabel": "press",
      "slug": "",
      "summary": "",
      "href": "https://seekingalpha.com/news/4603033-insider-trades-microsoft-tesla-pfizer-among-notable-names"
    },
    {
      "category": "product",
      "categoryLabel": "PRODUCT · 차량·에너지·옵티머스",
      "time": "11h ago",
      "pubDate": "2026-06-13T14:47:27.000Z",
      "title": "New Tesla Supercharger: Sibiu, Romania - Calea Șurii Mari (12 stalls)",
      "body": "New Tesla Supercharger: Sibiu, Romania - Calea Șurii Mari (12 stalls) https://t.co/Ho4HvgWiFW https://t.co/CN1QmNyskK",
      "sourceName": "Tesla Charging (X)",
      "sourceLabel": "official",
      "slug": "",
      "summary": "",
      "href": "https://x.com/TeslaCharging/status/2065808273102832023"
    },
    {
      "category": "fsd",
      "categoryLabel": "FSD · 자율·로보택시",
      "time": "11h ago",
      "pubDate": "2026-06-13T14:25:34.000Z",
      "title": "I wish there were more supply chain conferences like this in the Bay Area that I could bring my kid to visit. When I …",
      "body": "I wish there were more supply chain conferences like this in the Bay Area that I could bring my kid to visit. When I was a student, I went to a few expos and conferences like this that later inspired me to become an engi…",
      "sourceName": "Yun-Ta Tsai (X)",
      "sourceLabel": "official",
      "slug": "",
      "summary": "",
      "href": "https://x.com/yunta_tsai/status/2065802766304600556"
    },
    {
      "category": "product",
      "categoryLabel": "PRODUCT · 차량·에너지·옵티머스",
      "time": "12h ago",
      "pubDate": "2026-06-13T13:50:56.000Z",
      "title": "Updated Tesla Cybertruck Prototype Shows Off New Features [Video]",
      "body": "Updated Tesla Cybertruck Prototype Shows Off New Features [Video] Not a Tesla App",
      "sourceName": "Not a Tesla App",
      "sourceLabel": "press",
      "slug": "",
      "summary": "",
      "href": "https://www.notateslaapp.com/news/1183/%3Ca%20href"
    }
  ]
}
