{
  "asOf": "2026-07-04 17:13 UTC 기준 · 카테고리당 top 5건",
  "items": [
    {
      "category": "fsd",
      "categoryLabel": "FSD · 자율·로보택시",
      "time": "1h ago",
      "pubDate": "2026-07-04T15:47:31.000Z",
      "title": "Tesla Driver Charged With Manslaughter For Texas Crash That Killed A Woman In Her Home",
      "body": "Tesla Driver Charged With Manslaughter For Texas Crash That Killed A Woman In Her Home Engadget",
      "sourceName": "Engadget",
      "sourceLabel": "press",
      "slug": "",
      "summary": "",
      "href": "https://www.engadget.com/2207957/tesla-driver-charged-manslaughter-texas-crash-killed-woman-in-home/"
    },
    {
      "category": "stock",
      "categoryLabel": "STOCK · 주가·실적",
      "time": "16h ago",
      "pubDate": "2026-07-04T00:49:46.000Z",
      "title": "Tesla’s strong Q2 deliveries: Four key drivers behind the surprise",
      "body": "Tesla’s strong Q2 deliveries: Four key drivers behind the surprise Teslarati",
      "sourceName": "Teslarati",
      "sourceLabel": "press",
      "slug": "",
      "summary": "",
      "href": "https://www.teslarati.com/tesla-strong-q2-deliveries-four-key-drivers-behind-the-surprise/"
    },
    {
      "category": "product",
      "categoryLabel": "PRODUCT · 차량·에너지·옵티머스",
      "time": "20h ago",
      "pubDate": "2026-07-03T21:15:43.000Z",
      "title": "Tesla Semi involved in first known fatal crash in Nevada",
      "body": "Tesla Semi involved in first known fatal crash in Nevada Teslarati",
      "sourceName": "Teslarati",
      "sourceLabel": "press",
      "slug": "",
      "summary": "",
      "href": "https://www.teslarati.com/tesla-semi-involved-first-known-fatal-crash-nevada/"
    },
    {
      "category": "fsd",
      "categoryLabel": "FSD · 자율·로보택시",
      "time": "1d ago",
      "pubDate": "2026-07-03T14:59:44.000Z",
      "title": "Tesla rolls out robotaxi service in Miami",
      "body": "Tesla rolls out robotaxi service in Miami Reuters",
      "sourceName": "Reuters",
      "sourceLabel": "press",
      "slug": "",
      "summary": "",
      "href": "https://www.reuters.com/business/autos-transportation/tesla-rolls-out-robotaxi-service-miami-2026-07-03/"
    },
    {
      "category": "musk",
      "categoryLabel": "ELON · 일론 소식",
      "time": "2d ago",
      "pubDate": "2026-07-03T01:00:00.000Z",
      "title": "India’s Space Industry Hunts for Its SpaceX Moment",
      "body": "India’s Space Industry Hunts for Its SpaceX Moment Bloomberg.com",
      "sourceName": "Bloomberg.com",
      "sourceLabel": "press",
      "slug": "",
      "summary": "",
      "href": "https://www.bloomberg.com/news/articles/2026-07-03/india-s-space-industry-hunts-for-its-spacex-moment"
    },
    {
      "category": "stock",
      "categoryLabel": "STOCK · 주가·실적",
      "time": "2d ago",
      "pubDate": "2026-07-02T22:21:35.000Z",
      "title": "Tesla driver charged with manslaughter over crash into Texas home",
      "body": "Tesla driver charged with manslaughter over crash into Texas home Reuters",
      "sourceName": "Reuters",
      "sourceLabel": "press",
      "slug": "",
      "summary": "",
      "href": "https://www.reuters.com/world/us/tesla-driver-charged-with-manslaughter-over-crash-into-texas-home-2026-07-02/"
    },
    {
      "category": "product",
      "categoryLabel": "PRODUCT · 차량·에너지·옵티머스",
      "time": "2d ago",
      "pubDate": "2026-07-02T22:21:35.000Z",
      "title": "Tesla driver charged with manslaughter over crash into Texas home",
      "body": "Tesla driver charged with manslaughter over crash into Texas home Reuters",
      "sourceName": "Reuters",
      "sourceLabel": "press",
      "slug": "",
      "summary": "",
      "href": "https://www.reuters.com/world/us/tesla-driver-charged-with-manslaughter-over-crash-into-texas-home-2026-07-02/"
    },
    {
      "category": "fsd",
      "categoryLabel": "FSD · 자율·로보택시",
      "time": "2d ago",
      "pubDate": "2026-07-02T22:21:35.000Z",
      "title": "Tesla driver charged with manslaughter over crash into Texas home",
      "body": "Tesla driver charged with manslaughter over crash into Texas home Reuters",
      "sourceName": "Reuters",
      "sourceLabel": "press",
      "slug": "",
      "summary": "",
      "href": "https://www.reuters.com/world/us/tesla-driver-charged-with-manslaughter-over-crash-into-texas-home-2026-07-02/"
    },
    {
      "category": "musk",
      "categoryLabel": "ELON · 일론 소식",
      "time": "2d ago",
      "pubDate": "2026-07-02T22:21:35.000Z",
      "title": "Tesla driver charged with manslaughter over crash into Texas home",
      "body": "Tesla driver charged with manslaughter over crash into Texas home Reuters",
      "sourceName": "Reuters",
      "sourceLabel": "press",
      "slug": "",
      "summary": "",
      "href": "https://www.reuters.com/world/us/tesla-driver-charged-with-manslaughter-over-crash-into-texas-home-2026-07-02/"
    },
    {
      "category": "musk",
      "categoryLabel": "ELON · 일론 소식",
      "time": "2d ago",
      "pubDate": "2026-07-02T21:30:40.000Z",
      "title": "Tesla’s Sales Beat Wasn’t Enough to Best BYD",
      "body": "Tesla’s Sales Beat Wasn’t Enough to Best BYD Bloomberg.com",
      "sourceName": "Bloomberg.com",
      "sourceLabel": "press",
      "slug": "",
      "summary": "",
      "href": "https://www.bloomberg.com/news/newsletters/2026-07-02/tesla-beat-sales-estimates-but-fell-short-of-byd?srnd"
    },
    {
      "category": "product",
      "categoryLabel": "PRODUCT · 차량·에너지·옵티머스",
      "time": "2d ago",
      "pubDate": "2026-07-02T21:19:48.000Z",
      "title": "Tesla launches six-seater Model Y L in US to boost sales",
      "body": "Tesla launches six-seater Model Y L in US to boost sales Reuters",
      "sourceName": "Reuters",
      "sourceLabel": "press",
      "slug": "",
      "summary": "",
      "href": "https://www.reuters.com/business/autos-transportation/tesla-launches-six-seater-model-y-l-us-boost-sales-2026-07-02/"
    },
    {
      "category": "stock",
      "categoryLabel": "STOCK · 주가·실적",
      "time": "2d ago",
      "pubDate": "2026-07-02T20:13:50.000Z",
      "title": "(TSLA) Tesla Vehicle Sales Climb 25%, Far Exceeding Analyst Estimates",
      "body": "(TSLA) Tesla Vehicle Sales Climb 25%, Far Exceeding Analyst Estimates Bloomberg.com",
      "sourceName": "Bloomberg.com",
      "sourceLabel": "press",
      "slug": "",
      "summary": "",
      "href": "https://www.bloomberg.com/news/articles/2026-07-02/tesla-vehicle-sales-climb-25-far-exceeding-analyst-estimates"
    },
    {
      "category": "product",
      "categoryLabel": "PRODUCT · 차량·에너지·옵티머스",
      "time": "2d ago",
      "pubDate": "2026-07-02T18:59:12.000Z",
      "title": "Tesla Says Three-Row Model Y SUV Now Available to US Customers",
      "body": "Tesla Says Three-Row Model Y SUV Now Available to US Customers Bloomberg.com",
      "sourceName": "Bloomberg.com",
      "sourceLabel": "press",
      "slug": "",
      "summary": "",
      "href": "https://www.bloomberg.com/news/articles/2026-07-02/tesla-says-three-row-model-y-suv-now-available-to-us-customers"
    },
    {
      "category": "stock",
      "categoryLabel": "STOCK · 주가·실적",
      "time": "2d ago",
      "pubDate": "2026-07-02T18:27:00.000Z",
      "title": "Deepwater's Gene Munster on why Tesla is seeing strong demand",
      "body": "Deepwater's Gene Munster on why Tesla is seeing strong demand CNBC",
      "sourceName": "CNBC",
      "sourceLabel": "press",
      "slug": "",
      "summary": "",
      "href": "https://www.cnbc.com/video/2026/07/02/deepwaters-gene-munster-on-why-tesla-is-seeing-strong-demand.html"
    },
    {
      "category": "stock",
      "categoryLabel": "STOCK · 주가·실적",
      "time": "2d ago",
      "pubDate": "2026-07-02T18:21:00.000Z",
      "title": "Tesla Driver Charged With Manslaughter After Crashing Into Texas Home, Killing Woman",
      "body": "Tesla Driver Charged With Manslaughter After Crashing Into Texas Home, Killing Woman WSJ",
      "sourceName": "WSJ",
      "sourceLabel": "press",
      "slug": "",
      "summary": "",
      "href": "https://www.wsj.com/business/autos/driver-charged-with-manslaughter-after-tesla-crashed-into-texas-home-killing-woman-inside-65e17279"
    },
    {
      "category": "fsd",
      "categoryLabel": "FSD · 자율·로보택시",
      "time": "2d ago",
      "pubDate": "2026-07-02T18:21:00.000Z",
      "title": "Tesla Driver Charged With Manslaughter After Crashing Into Texas Home, Killing Woman",
      "body": "Tesla Driver Charged With Manslaughter After Crashing Into Texas Home, Killing Woman WSJ",
      "sourceName": "WSJ",
      "sourceLabel": "press",
      "slug": "",
      "summary": "",
      "href": "https://www.wsj.com/business/autos/driver-charged-with-manslaughter-after-tesla-crashed-into-texas-home-killing-woman-inside-65e17279"
    },
    {
      "category": "musk",
      "categoryLabel": "ELON · 일론 소식",
      "time": "2d ago",
      "pubDate": "2026-07-02T18:21:00.000Z",
      "title": "Tesla Driver Charged With Manslaughter After Crashing Into Texas Home, Killing Woman",
      "body": "Tesla Driver Charged With Manslaughter After Crashing Into Texas Home, Killing Woman WSJ",
      "sourceName": "WSJ",
      "sourceLabel": "press",
      "slug": "",
      "summary": "",
      "href": "https://www.wsj.com/business/autos/driver-charged-with-manslaughter-after-tesla-crashed-into-texas-home-killing-woman-inside-65e17279"
    },
    {
      "category": "musk",
      "categoryLabel": "ELON · 일론 소식",
      "time": "2d ago",
      "pubDate": "2026-07-02T17:40:00.000Z",
      "title": "Tesla sales jumped last quarter in a possible sign the worst of the Musk backlash is behind it",
      "body": "Tesla sales jumped last quarter in a possible sign the worst of the Musk backlash is behind it AP News",
      "sourceName": "AP News",
      "sourceLabel": "press",
      "slug": "",
      "summary": "",
      "href": "https://apnews.com/article/tesla-musk-byd-sales-deliveries-europe-6c997dddb6775c0a8bd74b993b66f0a7"
    },
    {
      "category": "product",
      "categoryLabel": "PRODUCT · 차량·에너지·옵티머스",
      "time": "2d ago",
      "pubDate": "2026-07-02T17:15:20.000Z",
      "title": "U.S. closes 2022 probe into 695,000 Tesla vehicles over unexpected braking",
      "body": "U.S. closes 2022 probe into 695,000 Tesla vehicles over unexpected braking Reuters",
      "sourceName": "Reuters",
      "sourceLabel": "press",
      "slug": "",
      "summary": "",
      "href": "https://www.reuters.com/legal/litigation/us-closes-2022-probe-into-695000-tesla-vehicles-over-unexpected-braking-2026-07-02/"
    },
    {
      "category": "fsd",
      "categoryLabel": "FSD · 자율·로보택시",
      "time": "2d ago",
      "pubDate": "2026-07-02T17:15:20.000Z",
      "title": "U.S. closes 2022 probe into 695,000 Tesla vehicles over unexpected braking",
      "body": "U.S. closes 2022 probe into 695,000 Tesla vehicles over unexpected braking Reuters",
      "sourceName": "Reuters",
      "sourceLabel": "press",
      "slug": "",
      "summary": "",
      "href": "https://www.reuters.com/legal/litigation/us-closes-2022-probe-into-695000-tesla-vehicles-over-unexpected-braking-2026-07-02/"
    }
  ]
}
