{
  "asOf": "2026-07-12 13:39 UTC 기준 · 카테고리당 top 5건",
  "items": [
    {
      "category": "musk",
      "categoryLabel": "ELON · 일론 소식",
      "time": "7m ago",
      "pubDate": "2026-07-12T13:33:00.000Z",
      "title": "Tesla merger with SpaceX won’t save investors, top analyst says",
      "body": "Tesla merger with SpaceX won’t save investors, top analyst says thestreet.com",
      "sourceName": "thestreet.com",
      "sourceLabel": "press",
      "slug": "",
      "summary": "",
      "href": "https://www.thestreet.com/investing/tesla-spacex-merger-wont-save-investors-bnp-paribas"
    },
    {
      "category": "musk",
      "categoryLabel": "ELON · 일론 소식",
      "time": "8m ago",
      "pubDate": "2026-07-12T13:31:38.000Z",
      "title": "SpaceX reveals Starship Flight 13 launch date",
      "body": "SpaceX is preparing for the 13th integrated flight test of its Starship system, with a targeted launch as early as Thursday, July 16. The 90-minute launch window opens at 5:45 p.m. CT from Starbase in South Texas. This c…",
      "sourceName": "www.teslarati.com",
      "sourceLabel": "press",
      "slug": "",
      "summary": "",
      "href": "https://www.teslarati.com/spacex-reveals-starship-flight-13-launch-date/"
    },
    {
      "category": "fsd",
      "categoryLabel": "FSD · 자율·로보택시",
      "time": "8m ago",
      "pubDate": "2026-07-12T13:31:04.000Z",
      "title": "This Week in Tesla: Model Y Tops Sales, NHTSA Demands Autonomous Vehicles Fix and More",
      "body": "This Week in Tesla: Model Y Tops Sales, NHTSA Demands Autonomous Vehicles Fix and More Benzinga",
      "sourceName": "Benzinga",
      "sourceLabel": "press",
      "slug": "",
      "summary": "",
      "href": "https://www.benzinga.com/markets/tech/26/07/60405206/this-week-in-tesla-model-y-tops-sales-nhtsa-demands-autonomous-vehicles-fix-and-more"
    },
    {
      "category": "fsd",
      "categoryLabel": "FSD · 자율·로보택시",
      "time": "17h ago",
      "pubDate": "2026-07-11T20:33:48.000Z",
      "title": "Tesla claims Cybercab driving employees at Giga Texas — in a parking lot",
      "body": "Tesla says “Cybercab employee rides at Giga Texas” are “starting soon” — its first stated step toward putting people inside the wheel-less, pedal-less robotaxi. But the announcement, spread across two Tesla accounts and …",
      "sourceName": "electrek.co",
      "sourceLabel": "press",
      "slug": "",
      "summary": "",
      "href": "https://electrek.co/2026/07/11/tesla-cybercab-giga-texas-parking-lot/"
    },
    {
      "category": "product",
      "categoryLabel": "PRODUCT · 차량·에너지·옵티머스",
      "time": "17h ago",
      "pubDate": "2026-07-11T20:17:48.000Z",
      "title": "Big shoes to fill, but I’m confident Optimus will not disappoint!!",
      "body": "Big shoes to fill, but I’m confident Optimus will not disappoint!! https://t.co/GUiqkyKddH",
      "sourceName": "Ashok Elluswamy (X)",
      "sourceLabel": "official",
      "slug": "",
      "summary": "",
      "href": "https://x.com/aelluswamy/status/2076038267548622988"
    },
    {
      "category": "musk",
      "categoryLabel": "ELON · 일론 소식",
      "time": "17h ago",
      "pubDate": "2026-07-11T20:17:06.000Z",
      "title": "Tesla self-driving enables safer mobility for senior citizens",
      "body": "Tesla self-driving enables safer mobility for senior citizens https://t.co/ubdd42XB1b",
      "sourceName": "Elon Musk (X)",
      "sourceLabel": "official",
      "slug": "",
      "summary": "",
      "href": "https://x.com/elonmusk/status/2076038090947166516"
    },
    {
      "category": "musk",
      "categoryLabel": "ELON · 일론 소식",
      "time": "20h ago",
      "pubDate": "2026-07-11T17:54:50.000Z",
      "title": "SpaceX discusses $1.6B Starlink deal with Italian government",
      "body": "SpaceX discusses $1.6B Starlink deal with Italian government Teslarati",
      "sourceName": "Teslarati",
      "sourceLabel": "press",
      "slug": "",
      "summary": "",
      "href": "https://www.teslarati.com/spacex-1-6-billion-starlink-deal-italy-government/"
    },
    {
      "category": "stock",
      "categoryLabel": "STOCK · 주가·실적",
      "time": "2d ago",
      "pubDate": "2026-07-10T20:14:00.000Z",
      "title": "Tesla Stock: Why Its Valuation Is Weighing on It Like an Anchor",
      "body": "Tesla Stock: Why Its Valuation Is Weighing on It Like an Anchor Barron's",
      "sourceName": "Barron's",
      "sourceLabel": "press",
      "slug": "",
      "summary": "",
      "href": "https://www.barrons.com/articles/tesla-stock-price-valuation-d10a4184"
    },
    {
      "category": "musk",
      "categoryLabel": "ELON · 일론 소식",
      "time": "2d ago",
      "pubDate": "2026-07-10T20:11:00.000Z",
      "title": "SpaceX Will Be ‘Worth More Than the Rest of Earth,’ Musk Says. How He Gets There.",
      "body": "SpaceX Will Be ‘Worth More Than the Rest of Earth,’ Musk Says. How He Gets There. Barron's",
      "sourceName": "Barron's",
      "sourceLabel": "press",
      "slug": "",
      "summary": "",
      "href": "https://www.barrons.com/articles/elon-musk-spacex-stock-worth-more-earth-cebedeeb"
    },
    {
      "category": "product",
      "categoryLabel": "PRODUCT · 차량·에너지·옵티머스",
      "time": "4d ago",
      "pubDate": "2026-07-09T00:37:00.000Z",
      "title": "Singapore Permit to Own Tesla Model 3 Jumps to Record High",
      "body": "Singapore Permit to Own Tesla Model 3 Jumps to Record High Bloomberg.com",
      "sourceName": "Bloomberg.com",
      "sourceLabel": "press",
      "slug": "",
      "summary": "",
      "href": "https://www.bloomberg.com/news/articles/2026-07-08/singapore-premiums-for-small-car-permits-at-record-99-700-high"
    },
    {
      "category": "product",
      "categoryLabel": "PRODUCT · 차량·에너지·옵티머스",
      "time": "5d ago",
      "pubDate": "2026-07-07T10:20:00.000Z",
      "title": "Ex-Tesla Scientist Unveils Plans For European Humanoid Robot",
      "body": "Ex-Tesla Scientist Unveils Plans For European Humanoid Robot Bloomberg.com",
      "sourceName": "Bloomberg.com",
      "sourceLabel": "press",
      "slug": "",
      "summary": "",
      "href": "https://www.bloomberg.com/news/articles/2026-07-07/ex-tesla-scientist-unveils-plans-for-european-humanoid-robot"
    },
    {
      "category": "product",
      "categoryLabel": "PRODUCT · 차량·에너지·옵티머스",
      "time": "6d ago",
      "pubDate": "2026-07-06T16:11:03.000Z",
      "title": "Rivian, Tesla and the 'Holly Index': How to trade the new EV Main Street battle",
      "body": "Rivian, Tesla and the 'Holly Index': How to trade the new EV Main Street battle CNBC",
      "sourceName": "CNBC",
      "sourceLabel": "press",
      "slug": "",
      "summary": "",
      "href": "https://www.cnbc.com/2026/07/06/rivian-tesla-and-the-holly-index-how-to-trade-the-new-ev-main-street-battle.html"
    },
    {
      "category": "product",
      "categoryLabel": "PRODUCT · 차량·에너지·옵티머스",
      "time": "7d ago",
      "pubDate": "2026-07-06T02:00:00.000Z",
      "title": "A Trucking Startup Aims to Challenge Tesla. Now, Paychecks Are Missing—and So Is a Truck.",
      "body": "A Trucking Startup Aims to Challenge Tesla. Now, Paychecks Are Missing—and So Is a Truck. WSJ",
      "sourceName": "WSJ",
      "sourceLabel": "press",
      "slug": "",
      "summary": "",
      "href": "https://www.wsj.com/business/autos/a-trucking-startup-aims-to-challenge-tesla-now-paychecks-are-missingand-so-is-a-truck-26e082cd"
    },
    {
      "category": "fsd",
      "categoryLabel": "FSD · 자율·로보택시",
      "time": "7d ago",
      "pubDate": "2026-07-06T02:00:00.000Z",
      "title": "A Trucking Startup Aims to Challenge Tesla. Now, Paychecks Are Missing—and So Is a Truck.",
      "body": "A Trucking Startup Aims to Challenge Tesla. Now, Paychecks Are Missing—and So Is a Truck. WSJ",
      "sourceName": "WSJ",
      "sourceLabel": "press",
      "slug": "",
      "summary": "",
      "href": "https://www.wsj.com/business/autos/a-trucking-startup-aims-to-challenge-tesla-now-paychecks-are-missingand-so-is-a-truck-26e082cd"
    },
    {
      "category": "fsd",
      "categoryLabel": "FSD · 자율·로보택시",
      "time": "9d ago",
      "pubDate": "2026-07-03T07:00:00.000Z",
      "title": "Tesla rolls out robotaxi service in Miami",
      "body": "Tesla rolls out robotaxi service in Miami Reuters",
      "sourceName": "Reuters",
      "sourceLabel": "press",
      "slug": "",
      "summary": "",
      "href": "https://www.reuters.com/business/autos-transportation/tesla-rolls-out-robotaxi-service-miami-2026-07-03/"
    },
    {
      "category": "fsd",
      "categoryLabel": "FSD · 자율·로보택시",
      "time": "10d ago",
      "pubDate": "2026-07-02T22:21:35.000Z",
      "title": "Tesla driver charged with manslaughter over crash into Texas home",
      "body": "Tesla driver charged with manslaughter over crash into Texas home Reuters",
      "sourceName": "Reuters",
      "sourceLabel": "press",
      "slug": "",
      "summary": "",
      "href": "https://www.reuters.com/world/us/tesla-driver-charged-with-manslaughter-over-crash-into-texas-home-2026-07-02/"
    },
    {
      "category": "stock",
      "categoryLabel": "STOCK · 주가·실적",
      "time": "10d ago",
      "pubDate": "2026-07-02T07:00:00.000Z",
      "title": "Tesla stock sinks 7% despite strong deliveries report, posting worst day in nearly a year",
      "body": "Tesla stock sinks 7% despite strong deliveries report, posting worst day in nearly a year CNBC",
      "sourceName": "CNBC",
      "sourceLabel": "press",
      "slug": "",
      "summary": "",
      "href": "https://www.cnbc.com/2026/07/02/tesla-tsla-q2-2026-vehicle-delivery-production.html"
    },
    {
      "category": "stock",
      "categoryLabel": "STOCK · 주가·실적",
      "time": "10d ago",
      "pubDate": "2026-07-02T07:00:00.000Z",
      "title": "Tesla Sales Jumped in Second Quarter",
      "body": "Tesla Sales Jumped in Second Quarter WSJ",
      "sourceName": "WSJ",
      "sourceLabel": "press",
      "slug": "",
      "summary": "",
      "href": "https://www.wsj.com/business/autos/tesla-sales-jumped-in-second-quarter-c9e2f067"
    },
    {
      "category": "stock",
      "categoryLabel": "STOCK · 주가·실적",
      "time": "101d ago",
      "pubDate": "2026-04-02T07:00:00.000Z",
      "title": "Tesla's stock suffers steepest drop of 2026 on disappointing deliveries report",
      "body": "Tesla's stock suffers steepest drop of 2026 on disappointing deliveries report CNBC",
      "sourceName": "CNBC",
      "sourceLabel": "press",
      "slug": "",
      "summary": "",
      "href": "https://www.cnbc.com/2026/04/02/tesla-tsla-q1-2026-vehicle-delivery-production.html"
    },
    {
      "category": "stock",
      "categoryLabel": "STOCK · 주가·실적",
      "time": "218d ago",
      "pubDate": "2025-12-06T06:21:03.000Z",
      "title": "MSFT, NVDA, NIO, PLTR, QS, SOFI, TLRY, TSLA, VZ - Stock Price, Quote",
      "body": "MSFT, NVDA, NIO, PLTR, QS, SOFI, TLRY, TSLA, VZ - Stock Price, Quote CNBC",
      "sourceName": "CNBC",
      "sourceLabel": "press",
      "slug": "",
      "summary": "",
      "href": "https://www.cnbc.com/quotes/MSFT,%20NVDA,%20NIO,%20PLTR,%20QS,%20SOFI,%20TLRY,%20TSLA,%20VZ"
    }
  ]
}
