{
  "asOf": "2026-06-25 16:29 UTC 기준 · 카테고리당 top 5건",
  "items": [
    {
      "category": "product",
      "categoryLabel": "PRODUCT · 차량·에너지·옵티머스",
      "time": "1h ago",
      "pubDate": "2026-06-25T15:26:12.000Z",
      "title": "Polestar says Trump administration forcing it to end US sales",
      "body": "Polestar says Trump administration forcing it to end US sales Reuters",
      "sourceName": "Reuters",
      "sourceLabel": "press",
      "slug": "",
      "summary": "",
      "href": "https://www.reuters.com/business/autos-transportation/us-denies-polestar-authorization-sell-vehicles-latest-strike-against-china-made-2026-06-25/"
    },
    {
      "category": "fsd",
      "categoryLabel": "FSD · 자율·로보택시",
      "time": "1h ago",
      "pubDate": "2026-06-25T15:26:12.000Z",
      "title": "Polestar says Trump administration forcing it to end US sales",
      "body": "Polestar says Trump administration forcing it to end US sales Reuters",
      "sourceName": "Reuters",
      "sourceLabel": "press",
      "slug": "",
      "summary": "",
      "href": "https://www.reuters.com/business/autos-transportation/us-denies-polestar-authorization-sell-vehicles-latest-strike-against-china-made-2026-06-25/"
    },
    {
      "category": "product",
      "categoryLabel": "PRODUCT · 차량·에너지·옵티머스",
      "time": "1h ago",
      "pubDate": "2026-06-25T15:08:18.000Z",
      "title": "Three New ETFs to Watch",
      "body": "Three New ETFs to Watch Bloomberg",
      "sourceName": "Bloomberg",
      "sourceLabel": "press",
      "slug": "",
      "summary": "",
      "href": "https://www.bloomberg.com/news/articles/2026-06-25/new-etfs-to-watch-2x-spacex-3x-ai-plus-bonds-and-bitcoin"
    },
    {
      "category": "musk",
      "categoryLabel": "ELON · 일론 소식",
      "time": "2h ago",
      "pubDate": "2026-06-25T14:59:50.000Z",
      "title": "DO NOT USE Consumer",
      "body": "DO NOT USE Consumer CNBC",
      "sourceName": "CNBC",
      "sourceLabel": "press",
      "slug": "",
      "summary": "",
      "href": "https://www.cnbc.com/consumers/"
    },
    {
      "category": "product",
      "categoryLabel": "PRODUCT · 차량·에너지·옵티머스",
      "time": "2h ago",
      "pubDate": "2026-06-25T14:59:10.000Z",
      "title": "Micron overtakes Meta, Tesla in market value amid relentless AI infrastructure demand",
      "body": "Micron overtakes Meta, Tesla in market value amid relentless AI infrastructure demand Reuters",
      "sourceName": "Reuters",
      "sourceLabel": "press",
      "slug": "",
      "summary": "",
      "href": "https://www.reuters.com/business/micron-overtakes-meta-market-value-amid-relentless-ai-infrastructure-demand-2026-06-25/"
    },
    {
      "category": "musk",
      "categoryLabel": "ELON · 일론 소식",
      "time": "2h ago",
      "pubDate": "2026-06-25T14:53:00.000Z",
      "title": "Meta Tried to Silence Her. Now She’s Suing.",
      "body": "Meta Tried to Silence Her. Now She’s Suing. WSJ",
      "sourceName": "WSJ",
      "sourceLabel": "press",
      "slug": "",
      "summary": "",
      "href": "https://www.wsj.com/us-news/law/meta-tried-to-silence-her-now-shes-suing-b228997c"
    },
    {
      "category": "stock",
      "categoryLabel": "STOCK · 주가·실적",
      "time": "3h ago",
      "pubDate": "2026-06-25T13:51:57.000Z",
      "title": "Tesla to ramp up production in Germany by 20%",
      "body": "Tesla to ramp up production in Germany by 20% CNBC",
      "sourceName": "CNBC",
      "sourceLabel": "press",
      "slug": "",
      "summary": "",
      "href": "https://www.cnbc.com/2026/06/25/tesla-to-ramp-up-production-in-germany-by-20percent.html"
    },
    {
      "category": "product",
      "categoryLabel": "PRODUCT · 차량·에너지·옵티머스",
      "time": "3h ago",
      "pubDate": "2026-06-25T13:51:57.000Z",
      "title": "Tesla to ramp up production in Germany by 20%",
      "body": "Tesla to ramp up production in Germany by 20% CNBC",
      "sourceName": "CNBC",
      "sourceLabel": "press",
      "slug": "",
      "summary": "",
      "href": "https://www.cnbc.com/2026/06/25/tesla-to-ramp-up-production-in-germany-by-20percent.html"
    },
    {
      "category": "stock",
      "categoryLabel": "STOCK · 주가·실적",
      "time": "3h ago",
      "pubDate": "2026-06-25T13:16:32.000Z",
      "title": "Tesla to ramp up production in Germany by 20%",
      "body": "Tesla to ramp up production in Germany by 20% Reuters",
      "sourceName": "Reuters",
      "sourceLabel": "press",
      "slug": "",
      "summary": "",
      "href": "https://www.reuters.com/business/autos-transportation/tesla-ramp-up-production-germany-by-20-2026-06-25/"
    },
    {
      "category": "product",
      "categoryLabel": "PRODUCT · 차량·에너지·옵티머스",
      "time": "3h ago",
      "pubDate": "2026-06-25T13:16:32.000Z",
      "title": "Tesla to ramp up production in Germany by 20%",
      "body": "Tesla to ramp up production in Germany by 20% Reuters",
      "sourceName": "Reuters",
      "sourceLabel": "press",
      "slug": "",
      "summary": "",
      "href": "https://www.reuters.com/business/autos-transportation/tesla-ramp-up-production-germany-by-20-2026-06-25/"
    },
    {
      "category": "fsd",
      "categoryLabel": "FSD · 자율·로보택시",
      "time": "3h ago",
      "pubDate": "2026-06-25T13:16:32.000Z",
      "title": "Tesla to ramp up production in Germany by 20%",
      "body": "Tesla to ramp up production in Germany by 20% Reuters",
      "sourceName": "Reuters",
      "sourceLabel": "press",
      "slug": "",
      "summary": "",
      "href": "https://www.reuters.com/business/autos-transportation/tesla-ramp-up-production-germany-by-20-2026-06-25/"
    },
    {
      "category": "fsd",
      "categoryLabel": "FSD · 자율·로보택시",
      "time": "3h ago",
      "pubDate": "2026-06-25T13:16:09.000Z",
      "title": "US proposes to drop brake pedal requirements for self-driving vehicles",
      "body": "US proposes to drop brake pedal requirements for self-driving vehicles Reuters",
      "sourceName": "Reuters",
      "sourceLabel": "press",
      "slug": "",
      "summary": "",
      "href": "https://www.reuters.com/business/autos-transportation/us-proposes-drop-brake-pedal-requirements-self-driving-vehicles-2026-06-25/"
    },
    {
      "category": "fsd",
      "categoryLabel": "FSD · 자율·로보택시",
      "time": "4h ago",
      "pubDate": "2026-06-25T12:53:00.000Z",
      "title": "Under Siege From Chinese Automakers, Volkswagen Sells Engine Business",
      "body": "Under Siege From Chinese Automakers, Volkswagen Sells Engine Business WSJ",
      "sourceName": "WSJ",
      "sourceLabel": "press",
      "slug": "",
      "summary": "",
      "href": "https://www.wsj.com/business/deals/volkswagen-to-sell-majority-stake-in-engine-unit-to-bain-capital-ae17cb9f"
    },
    {
      "category": "musk",
      "categoryLabel": "ELON · 일론 소식",
      "time": "4h ago",
      "pubDate": "2026-06-25T12:34:04.000Z",
      "title": "TOP PRO NEWS",
      "body": "TOP PRO NEWS CNBC",
      "sourceName": "CNBC",
      "sourceLabel": "press",
      "slug": "",
      "summary": "",
      "href": "https://www.cnbc.com/pro/"
    },
    {
      "category": "stock",
      "categoryLabel": "STOCK · 주가·실적",
      "time": "4h ago",
      "pubDate": "2026-06-25T12:26:46.000Z",
      "title": "Here are Thursday's biggest analyst calls: Micron, Apple, Intel, SanDisk, Netflix, Qualcomm, CoreWeave & more",
      "body": "Here are Thursday's biggest analyst calls: Micron, Apple, Intel, SanDisk, Netflix, Qualcomm, CoreWeave & more CNBC",
      "sourceName": "CNBC",
      "sourceLabel": "press",
      "slug": "",
      "summary": "",
      "href": "https://www.cnbc.com/2026/06/25/thursdays-biggest-analyst-calls-include-micron-and-apple.html"
    },
    {
      "category": "musk",
      "categoryLabel": "ELON · 일론 소식",
      "time": "5h ago",
      "pubDate": "2026-06-25T11:52:23.000Z",
      "title": "Germany",
      "body": "Germany WSJ",
      "sourceName": "WSJ",
      "sourceLabel": "press",
      "slug": "",
      "summary": "",
      "href": "https://www.wsj.com/topics/place/germany"
    },
    {
      "category": "fsd",
      "categoryLabel": "FSD · 자율·로보택시",
      "time": "6h ago",
      "pubDate": "2026-06-25T10:42:53.000Z",
      "title": "Russia hits Ukrainian locomotives and fuel stations, leaving one dead",
      "body": "Russia hits Ukrainian locomotives and fuel stations, leaving one dead Reuters",
      "sourceName": "Reuters",
      "sourceLabel": "press",
      "slug": "",
      "summary": "",
      "href": "https://www.reuters.com/world/russia-hits-ukrainian-locomotives-fuel-stations-leaving-one-dead-2026-06-25/"
    },
    {
      "category": "musk",
      "categoryLabel": "ELON · 일론 소식",
      "time": "6h ago",
      "pubDate": "2026-06-25T10:34:35.000Z",
      "title": "Wall Street trading to surge as Russell 1000 index set to add SpaceX, small-cap stocks",
      "body": "Wall Street trading to surge as Russell 1000 index set to add SpaceX, small-cap stocks Reuters",
      "sourceName": "Reuters",
      "sourceLabel": "press",
      "slug": "",
      "summary": "",
      "href": "https://www.reuters.com/business/wall-street-trading-surge-russell-1000-index-set-add-spacex-small-cap-stocks-2026-06-25/"
    },
    {
      "category": "stock",
      "categoryLabel": "STOCK · 주가·실적",
      "time": "6h ago",
      "pubDate": "2026-06-25T10:03:22.000Z",
      "title": "Insight: China's carmakers rush to Canada as a ‘practice run’ for US sales",
      "body": "Insight: China's carmakers rush to Canada as a ‘practice run’ for US sales Reuters",
      "sourceName": "Reuters",
      "sourceLabel": "press",
      "slug": "",
      "summary": "",
      "href": "https://www.reuters.com/business/autos-transportation/chinas-carmakers-rush-canada-practice-run-us-sales-2026-06-25/"
    },
    {
      "category": "stock",
      "categoryLabel": "STOCK · 주가·실적",
      "time": "7h ago",
      "pubDate": "2026-06-25T09:26:17.000Z",
      "title": "Micron is up 10% after blockbuster earnings, but has pulled back from highs",
      "body": "Micron is up 10% after blockbuster earnings, but has pulled back from highs CNBC",
      "sourceName": "CNBC",
      "sourceLabel": "press",
      "slug": "",
      "summary": "",
      "href": "https://www.cnbc.com/2026/06/25/micron-stock-3q-earnings-memory.html"
    }
  ]
}
